huangjb_sqlalchemy/__init__.py
huangjb_sqlalchemy/_lib_build/sqlalchemy/__init__.pyc
huangjb_sqlalchemy/_lib_build/sqlalchemy/events.pyc
huangjb_sqlalchemy/_lib_build/sqlalchemy/exc.pyc
huangjb_sqlalchemy/_lib_build/sqlalchemy/inspection.pyc
huangjb_sqlalchemy/_lib_build/sqlalchemy/log.pyc
huangjb_sqlalchemy/_lib_build/sqlalchemy/py.typed
huangjb_sqlalchemy/_lib_build/sqlalchemy/schema.pyc
huangjb_sqlalchemy/_lib_build/sqlalchemy/types.pyc
huangjb_sqlalchemy/_lib_build/sqlalchemy/connectors/__init__.pyc
huangjb_sqlalchemy/_lib_build/sqlalchemy/connectors/aioodbc.pyc
huangjb_sqlalchemy/_lib_build/sqlalchemy/connectors/asyncio.pyc
huangjb_sqlalchemy/_lib_build/sqlalchemy/connectors/pyodbc.pyc
huangjb_sqlalchemy/_lib_build/sqlalchemy/cyextension/__init__.pyc
huangjb_sqlalchemy/_lib_build/sqlalchemy/cyextension/collections.cpython-313t-arm-linux-gnueabihf.so
huangjb_sqlalchemy/_lib_build/sqlalchemy/cyextension/collections.pyx
huangjb_sqlalchemy/_lib_build/sqlalchemy/cyextension/immutabledict.cpython-313t-arm-linux-gnueabihf.so
huangjb_sqlalchemy/_lib_build/sqlalchemy/cyextension/immutabledict.pxd
huangjb_sqlalchemy/_lib_build/sqlalchemy/cyextension/immutabledict.pyx
huangjb_sqlalchemy/_lib_build/sqlalchemy/cyextension/processors.cpython-313t-arm-linux-gnueabihf.so
huangjb_sqlalchemy/_lib_build/sqlalchemy/cyextension/processors.pyx
huangjb_sqlalchemy/_lib_build/sqlalchemy/cyextension/resultproxy.cpython-313t-arm-linux-gnueabihf.so
huangjb_sqlalchemy/_lib_build/sqlalchemy/cyextension/resultproxy.pyx
huangjb_sqlalchemy/_lib_build/sqlalchemy/cyextension/util.cpython-313t-arm-linux-gnueabihf.so
huangjb_sqlalchemy/_lib_build/sqlalchemy/cyextension/util.pyx
huangjb_sqlalchemy/_lib_build/sqlalchemy/dialects/__init__.pyc
huangjb_sqlalchemy/_lib_build/sqlalchemy/dialects/_typing.pyc
huangjb_sqlalchemy/_lib_build/sqlalchemy/dialects/type_migration_guidelines.txt
huangjb_sqlalchemy/_lib_build/sqlalchemy/dialects/mssql/__init__.pyc
huangjb_sqlalchemy-2.0.41.dist-info/METADATA
huangjb_sqlalchemy-2.0.41.dist-info/WHEEL
huangjb_sqlalchemy-2.0.41.dist-info/top_level.txt
huangjb_sqlalchemy-2.0.41.dist-info/RECORD
